dagtools/__init__.py
dagtools/convert.py
dagtools/tests/__init__.py
dagtools/tests/test_convert.py
dagtools-0.0.2.dist-info/LICENSE
dagtools-0.0.2.dist-info/METADATA
dagtools-0.0.2.dist-info/WHEEL
dagtools-0.0.2.dist-info/top_level.txt
dagtools-0.0.2.dist-info/RECORD
