Metadata-Version: 2.1
Name: dagtools
Version: 0.0.2
Summary: Tools for manipulating Directed Acyclic Graphs in Python
Home-page: http://github.com/JWKennington/dagtools
Author: James W. Kennington
Author-email: jameswkennington@gmail.com
License: MIT
Platform: UNKNOWN
